[
    {
        "active": true,
        "alias": "Annie",
        "banVoPath": "/lol-game-data/assets/v1/champion-ban-vo/1.ogg",
        "baseLoadScreenPath": "/lol-game-data/assets/ASSETS/Characters/Annie/Skins/Base/AnnieLoadScreen.jpg",
        "baseSplashPath": "/lol-game-data/assets/v1/champion-splashes/1/1000.jpg",
        "botEnabled": true,
        "chooseVoPath": "/lol-game-data/assets/v1/champion-choose-vo/1.ogg",
        "disabledQueues": [],
        "freeToPlay": false,
        "id": 1,
        "name": "Annie",
        "ownership": {
            "freeToPlayReward": false,
            "owned": true,
            "rental": {
                "endDate": 0,
                "purchaseDate": 1433410738000,
                "rented": false,
                "winCountRemaining": 0
            }
        },
        "purchased": 1433410738000,
        "rankedPlayEnabled": true,
        "roles": [
            "mage"
        ],
        "squarePortraitPath": "/lol-game-data/assets/v1/champion-icons/1.png",
        "stingerSfxPath": "/lol-game-data/assets/v1/champion-sfx-audios/1.ogg",
        "title": "the Dark Child"
    },
    {
        "active": true,
        "alias": "Olaf",
        "banVoPath": "/lol-game-data/assets/v1/champion-ban-vo/2.ogg",
        "baseLoadScreenPath": "/lol-game-data/assets/ASSETS/Characters/Olaf/Skins/Base/OlafLoadScreen.jpg",
        "baseSplashPath": "/lol-game-data/assets/v1/champion-splashes/2/2000.jpg",
        "botEnabled": false,
        "chooseVoPath": "/lol-game-data/assets/v1/champion-choose-vo/2.ogg",
        "disabledQueues": [],
        "freeToPlay": false,
        "id": 2,
        "name": "Olaf",
        "ownership": {
            "freeToPlayReward": false,
            "owned": true,
            "rental": {
                "endDate": 0,
                "purchaseDate": 1596384580000,
                "rented": false,
                "winCountRemaining": 0
            }
        },
        "purchased": 1596384580000,
        "rankedPlayEnabled": true,
        "roles": [
            "fighter",
            "tank"
        ],
        "squarePortraitPath": "/lol-game-data/assets/v1/champion-icons/2.png",
        "stingerSfxPath": "/lol-game-data/assets/v1/champion-sfx-audios/2.ogg",
        "title": "the Berserker"
    },
    {
        "active": true,
        "alias": "TwistedFate",
        "banVoPath": "/lol-game-data/assets/v1/champion-ban-vo/4.ogg",
        "baseLoadScreenPath": "/lol-game-data/assets/ASSETS/Characters/TwistedFate/skins/base/TwistedFateLoadScreen.jpg",
        "baseSplashPath": "/lol-game-data/assets/v1/champion-splashes/4/4000.jpg",
        "botEnabled": false,
        "chooseVoPath": "/lol-game-data/assets/v1/champion-choose-vo/4.ogg",
        "disabledQueues": [],
        "freeToPlay": false,
        "id": 4,
        "name": "Twisted Fate",
        "ownership": {
            "freeToPlayReward": false,
            "owned": true,
            "rental": {
                "endDate": 0,
                "purchaseDate": 1493585670000,
                "rented": false,
                "winCountRemaining": 0
            }
        },
        "purchased": 1493585670000,
        "rankedPlayEnabled": true,
        "roles": [
            "mage"
        ],
        "squarePortraitPath": "/lol-game-data/assets/v1/champion-icons/4.png",
        "stingerSfxPath": "/lol-game-data/assets/v1/champion-sfx-audios/4.ogg",
        "title": "the Card Master"
    },
    {
        "active": true,
        "alias": "XinZhao",
        "banVoPath": "/lol-game-data/assets/v1/champion-ban-vo/5.ogg",
        "baseLoadScreenPath": "/lol-game-data/assets/ASSETS/Characters/XinZhao/Skins/Base/XinZhaoLoadScreen.jpg",
        "baseSplashPath": "/lol-game-data/assets/v1/champion-splashes/5/5000.jpg",
        "botEnabled": false,
        "chooseVoPath": "/lol-game-data/assets/v1/champion-choose-vo/5.ogg",
        "disabledQueues": [],
        "freeToPlay": false,
        "id": 5,
        "name": "Xin Zhao",
        "ownership": {
            "freeToPlayReward": false,
            "owned": true,
            "rental": {
                "endDate": 0,
                "purchaseDate": 1629054905000,
                "rented": false,
                "winCountRemaining": 0
            }
        },
        "purchased": 1629054905000,
        "rankedPlayEnabled": true,
        "roles": [
            "fighter",
            "assassin"
        ],
        "squarePortraitPath": "/lol-game-data/assets/v1/champion-icons/5.png",
        "stingerSfxPath": "/lol-game-data/assets/v1/champion-sfx-audios/5.ogg",
        "title": "the Seneschal of Demacia"
    },
    {
        "active": true,
        "alias": "Leblanc",
        "banVoPath": "/lol-game-data/assets/v1/champion-ban-vo/7.ogg",
        "baseLoadScreenPath": "/lol-game-data/assets/ASSETS/Characters/Leblanc/Skins/Base/LeblancLoadScreen.jpg",
        "baseSplashPath": "/lol-game-data/assets/v1/champion-splashes/7/7000.jpg",
        "botEnabled": false,
        "chooseVoPath": "/lol-game-data/assets/v1/champion-choose-vo/7.ogg",
        "disabledQueues": [],
        "freeToPlay": true,
        "id": 7,
        "name": "LeBlanc",
        "ownership": {
            "freeToPlayReward": false,
            "owned": true,
            "rental": {
                "endDate": 0,
                "purchaseDate": 1590950578000,
                "rented": false,
                "winCountRemaining": 0
            }
        },
        "purchased": 1590950578000,
        "rankedPlayEnabled": true,
        "roles": [
            "assassin",
            "mage"
        ],
        "squarePortraitPath": "/lol-game-data/assets/v1/champion-icons/7.png",
        "stingerSfxPath": "/lol-game-data/assets/v1/champion-sfx-audios/7.ogg",
        "title": "the Deceiver"
    },
    {
        "active": true,
        "alias": "Kayle",
        "banVoPath": "/lol-game-data/assets/v1/champion-ban-vo/10.ogg",
        "baseLoadScreenPath": "/lol-game-data/assets/ASSETS/Characters/Kayle/Skins/Base/KayleLoadScreen.jpg",
        "baseSplashPath": "/lol-game-data/assets/v1/champion-splashes/10/10000.jpg",
        "botEnabled": true,
        "chooseVoPath": "/lol-game-data/assets/v1/champion-choose-vo/10.ogg",
        "disabledQueues": [],
        "freeToPlay": false,
        "id": 10,
        "name": "Kayle",
        "ownership": {
            "freeToPlayReward": false,
            "owned": true,
            "rental": {
                "endDate": 0,
                "purchaseDate": 1433410780000,
                "rented": false,
                "winCountRemaining": 0
            }
        },
        "purchased": 1433410780000,
        "rankedPlayEnabled": true,
        "roles": [
            "fighter",
            "support"
        ],
        "squarePortraitPath": "/lol-game-data/assets/v1/champion-icons/10.png",
        "stingerSfxPath": "/lol-game-data/assets/v1/champion-sfx-audios/10.ogg",
        "title": "the Righteous"
    },
    {
        "active": true,
        "alias": "MasterYi",
        "banVoPath": "/lol-game-data/assets/v1/champion-ban-vo/11.ogg",
        "baseLoadScreenPath": "/lol-game-data/assets/ASSETS/Characters/MasterYi/Skins/Base/MasterYiLoadScreen.jpg",
        "baseSplashPath": "/lol-game-data/assets/v1/champion-splashes/11/11000.jpg",
        "botEnabled": true,
        "chooseVoPath": "/lol-game-data/assets/v1/champion-choose-vo/11.ogg",
        "disabledQueues": [],
        "freeToPlay": false,
        "id": 11,
        "name": "Master Yi",
        "ownership": {
            "freeToPlayReward": false,
            "owned": true,
            "rental": {
                "endDate": 0,
                "purchaseDate": 1408818554000,
                "rented": false,
                "winCountRemaining": 0
            }
        },
        "purchased": 1408818554000,
        "rankedPlayEnabled": true,
        "roles": [
            "assassin",
            "fighter"
        ],
        "squarePortraitPath": "/lol-game-data/assets/v1/champion-icons/11.png",
        "stingerSfxPath": "/lol-game-data/assets/v1/champion-sfx-audios/11.ogg",
        "title": "the Wuju Bladesman"
    },
    {
        "active": true,
        "alias": "Alistar",
        "banVoPath": "/lol-game-data/assets/v1/champion-ban-vo/12.ogg",
        "baseLoadScreenPath": "/lol-game-data/assets/ASSETS/Characters/Alistar/Skins/Base/AlistarLoadScreen.jpg",
        "baseSplashPath": "/lol-game-data/assets/v1/champion-splashes/12/12000.jpg",
        "botEnabled": true,
        "chooseVoPath": "/lol-game-data/assets/v1/champion-choose-vo/12.ogg",
        "disabledQueues": [],
        "freeToPlay": false,
        "id": 12,
        "name": "Alistar",
        "ownership": {
            "freeToPlayReward": false,
            "owned": true,
            "rental": {
                "endDate": 0,
                "purchaseDate": 1433410818000,
                "rented": false,
                "winCountRemaining": 0
            }
        },
        "purchased": 1433410818000,
        "rankedPlayEnabled": true,
        "roles": [
            "tank",
            "support"
        ],
        "squarePortraitPath": "/lol-game-data/assets/v1/champion-icons/12.png",
        "stingerSfxPath": "/lol-game-data/assets/v1/champion-sfx-audios/12.ogg",
        "title": "the Minotaur"
    },
    {
        "active": true,
        "alias": "Ryze",
        "banVoPath": "/lol-game-data/assets/v1/champion-ban-vo/13.ogg",
        "baseLoadScreenPath": "/lol-game-data/assets/ASSETS/Characters/Ryze/Skins/Base/RyzeLoadScreen.jpg",
        "baseSplashPath": "/lol-game-data/assets/v1/champion-splashes/13/13000.jpg",
        "botEnabled": true,
        "chooseVoPath": "/lol-game-data/assets/v1/champion-choose-vo/13.ogg",
        "disabledQueues": [],
        "freeToPlay": false,
        "id": 13,
        "name": "Ryze",
        "ownership": {
            "freeToPlayReward": false,
            "owned": true,
            "rental": {
                "endDate": 0,
                "purchaseDate": 1433410800000,
                "rented": false,
                "winCountRemaining": 0
            }
        },
        "purchased": 1433410800000,
        "rankedPlayEnabled": true,
        "roles": [
            "mage",
            "fighter"
        ],
        "squarePortraitPath": "/lol-game-data/assets/v1/champion-icons/13.png",
        "stingerSfxPath": "/lol-game-data/assets/v1/champion-sfx-audios/13.ogg",
        "title": "the Rune Mage"
    },
    {
        "active": true,
        "alias": "Sivir",
        "banVoPath": "/lol-game-data/assets/v1/champion-ban-vo/15.ogg",
        "baseLoadScreenPath": "/lol-game-data/assets/ASSETS/Characters/Sivir/Skins/Base/SivirLoadScreen.jpg",
        "baseSplashPath": "/lol-game-data/assets/v1/champion-splashes/15/15000.jpg",
        "botEnabled": true,
        "chooseVoPath": "/lol-game-data/assets/v1/champion-choose-vo/15.ogg",
        "disabledQueues": [],
        "freeToPlay": false,
        "id": 15,
        "name": "Sivir",
        "ownership": {
            "freeToPlayReward": false,
            "owned": true,
            "rental": {
                "endDate": 0,
                "purchaseDate": 1433410804000,
                "rented": false,
                "winCountRemaining": 0
            }
        },
        "purchased": 1433410804000,
        "rankedPlayEnabled": true,
        "roles": [
            "marksman"
        ],
        "squarePortraitPath": "/lol-game-data/assets/v1/champion-icons/15.png",
        "stingerSfxPath": "/lol-game-data/assets/v1/champion-sfx-audios/15.ogg",
        "title": "the Battle Mistress"
    },
    {
        "active": true,
        "alias": "Soraka",
        "banVoPath": "/lol-game-data/assets/v1/champion-ban-vo/16.ogg",
        "baseLoadScreenPath": "/lol-game-data/assets/ASSETS/Characters/Soraka/Skins/Base/SorakaLoadScreen.jpg",
        "baseSplashPath": "/lol-game-data/assets/v1/champion-splashes/16/16000.jpg",
        "botEnabled": true,
        "chooseVoPath": "/lol-game-data/assets/v1/champion-choose-vo/16.ogg",
        "disabledQueues": [],
        "freeToPlay": false,
        "id": 16,
        "name": "Soraka",
        "ownership": {
            "freeToPlayReward": false,
            "owned": true,
            "rental": {
                "endDate": 0,
                "purchaseDate": 1433410809000,
                "rented": false,
                "winCountRemaining": 0
            }
        },
        "purchased": 1433410809000,
        "rankedPlayEnabled": true,
        "roles": [
            "support",
            "mage"
        ],
        "squarePortraitPath": "/lol-game-data/assets/v1/champion-icons/16.png",
        "stingerSfxPath": "/lol-game-data/assets/v1/champion-sfx-audios/16.ogg",
        "title": "the Starchild"
    },
    {
        "active": true,
        "alias": "Tristana",
        "banVoPath": "/lol-game-data/assets/v1/champion-ban-vo/18.ogg",
        "baseLoadScreenPath": "/lol-game-data/assets/ASSETS/Characters/Tristana/Skins/Base/TristanaLoadScreen.jpg",
        "baseSplashPath": "/lol-game-data/assets/v1/champion-splashes/18/18000.jpg",
        "botEnabled": true,
        "chooseVoPath": "/lol-game-data/assets/v1/champion-choose-vo/18.ogg",
        "disabledQueues": [],
        "freeToPlay": false,
        "id": 18,
        "name": "Tristana",
        "ownership": {
            "freeToPlayReward": false,
            "owned": true,
            "rental": {
                "endDate": 0,
                "purchaseDate": 1396542424000,
                "rented": false,
                "winCountRemaining": 0
            }
        },
        "purchased": 1396542424000,
        "rankedPlayEnabled": true,
        "roles": [
            "marksman",
            "assassin"
        ],
        "squarePortraitPath": "/lol-game-data/assets/v1/champion-icons/18.png",
        "stingerSfxPath": "/lol-game-data/assets/v1/champion-sfx-audios/18.ogg",
        "title": "the Yordle Gunner"
    },
    {
        "active": true,
        "alias": "Warwick",
        "banVoPath": "/lol-game-data/assets/v1/champion-ban-vo/19.ogg",
        "baseLoadScreenPath": "/lol-game-data/assets/ASSETS/Characters/Warwick/Skins/Base/WarwickLoadscreen.jpg",
        "baseSplashPath": "/lol-game-data/assets/v1/champion-splashes/19/19000.jpg",
        "botEnabled": true,
        "chooseVoPath": "/lol-game-data/assets/v1/champion-choose-vo/19.ogg",
        "disabledQueues": [],
        "freeToPlay": false,
        "id": 19,
        "name": "Warwick",
        "ownership": {
            "freeToPlayReward": false,
            "owned": true,
            "rental": {
                "endDate": 0,
                "purchaseDate": 1433410814000,
                "rented": false,
                "winCountRemaining": 0
            }
        },
        "purchased": 1433410814000,
        "rankedPlayEnabled": true,
        "roles": [
            "fighter",
            "tank"
        ],
        "squarePortraitPath": "/lol-game-data/assets/v1/champion-icons/19.png",
        "stingerSfxPath": "/lol-game-data/assets/v1/champion-sfx-audios/19.ogg",
        "title": "the Uncaged Wrath of Zaun"
    },
    {
        "active": true,
        "alias": "Nunu",
        "banVoPath": "/lol-game-data/assets/v1/champion-ban-vo/20.ogg",
        "baseLoadScreenPath": "/lol-game-data/assets/ASSETS/Characters/Nunu/Skins/Base/NunuLoadScreen.jpg",
        "baseSplashPath": "/lol-game-data/assets/v1/champion-splashes/20/20000.jpg",
        "botEnabled": false,
        "chooseVoPath": "/lol-game-data/assets/v1/champion-choose-vo/20.ogg",
        "disabledQueues": [],
        "freeToPlay": false,
        "id": 20,
        "name": "Nunu & Willump",
        "ownership": {
            "freeToPlayReward": false,
            "owned": true,
            "rental": {
                "endDate": 0,
                "purchaseDate": 1433410787000,
                "rented": false,
                "winCountRemaining": 0
            }
        },
        "purchased": 1433410787000,
        "rankedPlayEnabled": true,
        "roles": [
            "tank",
            "fighter"
        ],
        "squarePortraitPath": "/lol-game-data/assets/v1/champion-icons/20.png",
        "stingerSfxPath": "/lol-game-data/assets/v1/champion-sfx-audios/20.ogg",
        "title": "the Boy and His Yeti"
    },
    {
        "active": true,
        "alias": "Ashe",
        "banVoPath": "/lol-game-data/assets/v1/champion-ban-vo/22.ogg",
        "baseLoadScreenPath": "/lol-game-data/assets/ASSETS/Characters/Ashe/Skins/Base/AsheLoadScreen.jpg",
        "baseSplashPath": "/lol-game-data/assets/v1/champion-splashes/22/22000.jpg",
        "botEnabled": true,
        "chooseVoPath": "/lol-game-data/assets/v1/champion-choose-vo/22.ogg",
        "disabledQueues": [],
        "freeToPlay": false,
        "id": 22,
        "name": "Ashe",
        "ownership": {
            "freeToPlayReward": false,
            "owned": true,
            "rental": {
                "endDate": 0,
                "purchaseDate": 1433410749000,
                "rented": false,
                "winCountRemaining": 0
            }
        },
        "purchased": 1433410749000,
        "rankedPlayEnabled": true,
        "roles": [
            "marksman",
            "support"
        ],
        "squarePortraitPath": "/lol-game-data/assets/v1/champion-icons/22.png",
        "stingerSfxPath": "/lol-game-data/assets/v1/champion-sfx-audios/22.ogg",
        "title": "the Frost Archer"
    },
    {
        "active": true,
        "alias": "Tryndamere",
        "banVoPath": "/lol-game-data/assets/v1/champion-ban-vo/23.ogg",
        "baseLoadScreenPath": "/lol-game-data/assets/ASSETS/Characters/Tryndamere/Skins/Base/TryndamereLoadScreen.jpg",
        "baseSplashPath": "/lol-game-data/assets/v1/champion-splashes/23/23000.jpg",
        "botEnabled": false,
        "chooseVoPath": "/lol-game-data/assets/v1/champion-choose-vo/23.ogg",
        "disabledQueues": [],
        "freeToPlay": false,
        "id": 23,
        "name": "Tryndamere",
        "ownership": {
            "freeToPlayReward": false,
            "owned": true,
            "rental": {
                "endDate": 0,
                "purchaseDate": 1593621400000,
                "rented": false,
                "winCountRemaining": 0
            }
        },
        "purchased": 1593621400000,
        "rankedPlayEnabled": true,
        "roles": [
            "fighter",
            "assassin"
        ],
        "squarePortraitPath": "/lol-game-data/assets/v1/champion-icons/23.png",
        "stingerSfxPath": "/lol-game-data/assets/v1/champion-sfx-audios/23.ogg",
        "title": "the Barbarian King"
    },
    {
        "active": true,
        "alias": "Jax",
        "banVoPath": "/lol-game-data/assets/v1/champion-ban-vo/24.ogg",
        "baseLoadScreenPath": "/lol-game-data/assets/ASSETS/Characters/Jax/Skins/Base/JaxLoadScreen.jpg",
        "baseSplashPath": "/lol-game-data/assets/v1/champion-splashes/24/24000.jpg",
        "botEnabled": true,
        "chooseVoPath": "/lol-game-data/assets/v1/champion-choose-vo/24.ogg",
        "disabledQueues": [],
        "freeToPlay": false,
        "id": 24,
        "name": "Jax",
        "ownership": {
            "freeToPlayReward": false,
            "owned": true,
            "rental": {
                "endDate": 0,
                "purchaseDate": 1433410890000,
                "rented": false,
                "winCountRemaining": 0
            }
        },
        "purchased": 1433410890000,
        "rankedPlayEnabled": true,
        "roles": [
            "fighter",
            "assassin"
        ],
        "squarePortraitPath": "/lol-game-data/assets/v1/champion-icons/24.png",
        "stingerSfxPath": "/lol-game-data/assets/v1/champion-sfx-audios/24.ogg",
        "title": "Grandmaster at Arms"
    },
    {
        "active": true,
        "alias": "Morgana",
        "banVoPath": "/lol-game-data/assets/v1/champion-ban-vo/25.ogg",
        "baseLoadScreenPath": "/lol-game-data/assets/ASSETS/Characters/Morgana/Skins/Base/MorganaLoadScreen.jpg",
        "baseSplashPath": "/lol-game-data/assets/v1/champion-splashes/25/25000.jpg",
        "botEnabled": true,
        "chooseVoPath": "/lol-game-data/assets/v1/champion-choose-vo/25.ogg",
        "disabledQueues": [],
        "freeToPlay": false,
        "id": 25,
        "name": "Morgana",
        "ownership": {
            "freeToPlayReward": false,
            "owned": true,
            "rental": {
                "endDate": 0,
                "purchaseDate": 1450376962000,
                "rented": false,
                "winCountRemaining": 0
            }
        },
        "purchased": 1450376962000,
        "rankedPlayEnabled": true,
        "roles": [
            "mage",
            "support"
        ],
        "squarePortraitPath": "/lol-game-data/assets/v1/champion-icons/25.png",
        "stingerSfxPath": "/lol-game-data/assets/v1/champion-sfx-audios/25.ogg",
        "title": "the Fallen"
    },
    {
        "active": true,
        "alias": "Zilean",
        "banVoPath": "/lol-game-data/assets/v1/champion-ban-vo/26.ogg",
        "baseLoadScreenPath": "/lol-game-data/assets/ASSETS/Characters/Zilean/Skins/Base/ZileanLoadScreen.jpg",
        "baseSplashPath": "/lol-game-data/assets/v1/champion-splashes/26/26000.jpg",
        "botEnabled": true,
        "chooseVoPath": "/lol-game-data/assets/v1/champion-choose-vo/26.ogg",
        "disabledQueues": [],
        "freeToPlay": false,
        "id": 26,
        "name": "Zilean",
        "ownership": {
            "freeToPlayReward": false,
            "owned": true,
            "rental": {
                "endDate": 0,
                "purchaseDate": 1512411001000,
                "rented": false,
                "winCountRemaining": 0
            }
        },
        "purchased": 1512411001000,
        "rankedPlayEnabled": true,
        "roles": [
            "support",
            "mage"
        ],
        "squarePortraitPath": "/lol-game-data/assets/v1/champion-icons/26.png",
        "stingerSfxPath": "/lol-game-data/assets/v1/champion-sfx-audios/26.ogg",
        "title": "the Chronokeeper"
    },
    {
        "active": true,
        "alias": "Evelynn",
        "banVoPath": "/lol-game-data/assets/v1/champion-ban-vo/28.ogg",
        "baseLoadScreenPath": "/lol-game-data/assets/ASSETS/Characters/Evelynn/Skins/Base/evelynnLoadScreen.jpg",
        "baseSplashPath": "/lol-game-data/assets/v1/champion-splashes/28/28000.jpg",
        "botEnabled": false,
        "chooseVoPath": "/lol-game-data/assets/v1/champion-choose-vo/28.ogg",
        "disabledQueues": [],
        "freeToPlay": true,
        "id": 28,
        "name": "Evelynn",
        "ownership": {
            "freeToPlayReward": false,
            "owned": false,
            "rental": {
                "endDate": 0,
                "purchaseDate": 0,
                "rented": false,
                "winCountRemaining": 0
            }
        },
        "purchased": 0,
        "rankedPlayEnabled": true,
        "roles": [
            "assassin",
            "mage"
        ],
        "squarePortraitPath": "/lol-game-data/assets/v1/champion-icons/28.png",
        "stingerSfxPath": "/lol-game-data/assets/v1/champion-sfx-audios/28.ogg",
        "title": "Agony's Embrace"
    },
    {
        "active": true,
        "alias": "Twitch",
        "banVoPath": "/lol-game-data/assets/v1/champion-ban-vo/29.ogg",
        "baseLoadScreenPath": "/lol-game-data/assets/ASSETS/Characters/Twitch/Skins/Base/TwitchLoadScreen.jpg",
        "baseSplashPath": "/lol-game-data/assets/v1/champion-splashes/29/29000.jpg",
        "botEnabled": false,
        "chooseVoPath": "/lol-game-data/assets/v1/champion-choose-vo/29.ogg",
        "disabledQueues": [],
        "freeToPlay": true,
        "id": 29,
        "name": "Twitch",
        "ownership": {
            "freeToPlayReward": false,
            "owned": true,
            "rental": {
                "endDate": 0,
                "purchaseDate": 1607636449000,
                "rented": false,
                "winCountRemaining": 0
            }
        },
        "purchased": 1607636449000,
        "rankedPlayEnabled": true,
        "roles": [
            "marksman",
            "assassin"
        ],
        "squarePortraitPath": "/lol-game-data/assets/v1/champion-icons/29.png",
        "stingerSfxPath": "/lol-game-data/assets/v1/champion-sfx-audios/29.ogg",
        "title": "the Plague Rat"
    },
    {
        "active": true,
        "alias": "Karthus",
        "banVoPath": "/lol-game-data/assets/v1/champion-ban-vo/30.ogg",
        "baseLoadScreenPath": "/lol-game-data/assets/ASSETS/Characters/Karthus/Skins/Base/KarthusLoadScreen.jpg",
        "baseSplashPath": "/lol-game-data/assets/v1/champion-splashes/30/30000.jpg",
        "botEnabled": true,
        "chooseVoPath": "/lol-game-data/assets/v1/champion-choose-vo/30.ogg",
        "disabledQueues": [],
        "freeToPlay": false,
        "id": 30,
        "name": "Karthus",
        "ownership": {
            "freeToPlayReward": false,
            "owned": true,
            "rental": {
                "endDate": 0,
                "purchaseDate": 1619192881000,
                "rented": false,
                "winCountRemaining": 0
            }
        },
        "purchased": 1619192881000,
        "rankedPlayEnabled": true,
        "roles": [
            "mage"
        ],
        "squarePortraitPath": "/lol-game-data/assets/v1/champion-icons/30.png",
        "stingerSfxPath": "/lol-game-data/assets/v1/champion-sfx-audios/30.ogg",
        "title": "the Deathsinger"
    },
    {
        "active": true,
        "alias": "Chogath",
        "banVoPath": "/lol-game-data/assets/v1/champion-ban-vo/31.ogg",
        "baseLoadScreenPath": "/lol-game-data/assets/ASSETS/Characters/Chogath/skins/base/ChogathLoadScreen.jpg",
        "baseSplashPath": "/lol-game-data/assets/v1/champion-splashes/31/31000.jpg",
        "botEnabled": true,
        "chooseVoPath": "/lol-game-data/assets/v1/champion-choose-vo/31.ogg",
        "disabledQueues": [],
        "freeToPlay": false,
        "id": 31,
        "name": "Cho'Gath",
        "ownership": {
            "freeToPlayReward": false,
            "owned": true,
            "rental": {
                "endDate": 0,
                "purchaseDate": 1433410886000,
                "rented": false,
                "winCountRemaining": 0
            }
        },
        "purchased": 1433410886000,
        "rankedPlayEnabled": true,
        "roles": [
            "tank",
            "mage"
        ],
        "squarePortraitPath": "/lol-game-data/assets/v1/champion-icons/31.png",
        "stingerSfxPath": "/lol-game-data/assets/v1/champion-sfx-audios/31.ogg",
        "title": "the Terror of the Void"
    },
    {
        "active": true,
        "alias": "Amumu",
        "banVoPath": "/lol-game-data/assets/v1/champion-ban-vo/32.ogg",
        "baseLoadScreenPath": "/lol-game-data/assets/ASSETS/Characters/Amumu/Skins/Base/AmumuLoadScreen.jpg",
        "baseSplashPath": "/lol-game-data/assets/v1/champion-splashes/32/32000.jpg",
        "botEnabled": true,
        "chooseVoPath": "/lol-game-data/assets/v1/champion-choose-vo/32.ogg",
        "disabledQueues": [],
        "freeToPlay": false,
        "id": 32,
        "name": "Amumu",
        "ownership": {
            "freeToPlayReward": false,
            "owned": true,
            "rental": {
                "endDate": 0,
                "purchaseDate": 1433410733000,
                "rented": false,
                "winCountRemaining": 0
            }
        },
        "purchased": 1433410733000,
        "rankedPlayEnabled": true,
        "roles": [
            "tank",
            "mage"
        ],
        "squarePortraitPath": "/lol-game-data/assets/v1/champion-icons/32.png",
        "stingerSfxPath": "/lol-game-data/assets/v1/champion-sfx-audios/32.ogg",
        "title": "the Sad Mummy"
    },
    {
        "active": true,
        "alias": "Rammus",
        "banVoPath": "/lol-game-data/assets/v1/champion-ban-vo/33.ogg",
        "baseLoadScreenPath": "/lol-game-data/assets/ASSETS/Characters/Rammus/skins/base/RammusLoadScreen.jpg",
        "baseSplashPath": "/lol-game-data/assets/v1/champion-splashes/33/33000.jpg",
        "botEnabled": true,
        "chooseVoPath": "/lol-game-data/assets/v1/champion-choose-vo/33.ogg",
        "disabledQueues": [],
        "freeToPlay": false,
        "id": 33,
        "name": "Rammus",
        "ownership": {
            "freeToPlayReward": false,
            "owned": true,
            "rental": {
                "endDate": 0,
                "purchaseDate": 1596384589000,
                "rented": false,
                "winCountRemaining": 0
            }
        },
        "purchased": 1596384589000,
        "rankedPlayEnabled": true,
        "roles": [
            "tank",
            "fighter"
        ],
        "squarePortraitPath": "/lol-game-data/assets/v1/champion-icons/33.png",
        "stingerSfxPath": "/lol-game-data/assets/v1/champion-sfx-audios/33.ogg",
        "title": "the Armordillo"
    },
    {
        "active": true,
        "alias": "Anivia",
        "banVoPath": "/lol-game-data/assets/v1/champion-ban-vo/34.ogg",
        "baseLoadScreenPath": "/lol-game-data/assets/ASSETS/Characters/Anivia/Skins/Base/AniviaLoadScreen.jpg",
        "baseSplashPath": "/lol-game-data/assets/v1/champion-splashes/34/34000.jpg",
        "botEnabled": false,
        "chooseVoPath": "/lol-game-data/assets/v1/champion-choose-vo/34.ogg",
        "disabledQueues": [],
        "freeToPlay": false,
        "id": 34,
        "name": "Anivia",
        "ownership": {
            "freeToPlayReward": false,
            "owned": true,
            "rental": {
                "endDate": 0,
                "purchaseDate": 1595962853000,
                "rented": false,
                "winCountRemaining": 0
            }
        },
        "purchased": 1595962853000,
        "rankedPlayEnabled": true,
        "roles": [
            "mage",
            "support"
        ],
        "squarePortraitPath": "/lol-game-data/assets/v1/champion-icons/34.png",
        "stingerSfxPath": "/lol-game-data/assets/v1/champion-sfx-audios/34.ogg",
        "title": "the Cryophoenix"
    },
    {
        "active": true,
        "alias": "Kassadin",
        "banVoPath": "/lol-game-data/assets/v1/champion-ban-vo/38.ogg",
        "baseLoadScreenPath": "/lol-game-data/assets/ASSETS/Characters/Kassadin/Skins/Base/KassadinLoadScreen.jpg",
        "baseSplashPath": "/lol-game-data/assets/v1/champion-splashes/38/38000.jpg",
        "botEnabled": false,
        "chooseVoPath": "/lol-game-data/assets/v1/champion-choose-vo/38.ogg",
        "disabledQueues": [],
        "freeToPlay": false,
        "id": 38,
        "name": "Kassadin",
        "ownership": {
            "freeToPlayReward": false,
            "owned": true,
            "rental": {
                "endDate": 0,
                "purchaseDate": 1596384739000,
                "rented": false,
                "winCountRemaining": 0
            }
        },
        "purchased": 1596384739000,
        "rankedPlayEnabled": true,
        "roles": [
            "assassin",
            "mage"
        ],
        "squarePortraitPath": "/lol-game-data/assets/v1/champion-icons/38.png",
        "stingerSfxPath": "/lol-game-data/assets/v1/champion-sfx-audios/38.ogg",
        "title": "the Void Walker"
    },
    {
        "active": true,
        "alias": "Gangplank",
        "banVoPath": "/lol-game-data/assets/v1/champion-ban-vo/41.ogg",
        "baseLoadScreenPath": "/lol-game-data/assets/ASSETS/Characters/Gangplank/Skins/Base/GangplankLoadScreen.jpg",
        "baseSplashPath": "/lol-game-data/assets/v1/champion-splashes/41/41000.jpg",
        "botEnabled": false,
        "chooseVoPath": "/lol-game-data/assets/v1/champion-choose-vo/41.ogg",
        "disabledQueues": [],
        "freeToPlay": false,
        "id": 41,
        "name": "Gangplank",
        "ownership": {
            "freeToPlayReward": false,
            "owned": true,
            "rental": {
                "endDate": 0,
                "purchaseDate": 1472993103000,
                "rented": false,
                "winCountRemaining": 0
            }
        },
        "purchased": 1472993103000,
        "rankedPlayEnabled": true,
        "roles": [
            "fighter"
        ],
        "squarePortraitPath": "/lol-game-data/assets/v1/champion-icons/41.png",
        "stingerSfxPath": "/lol-game-data/assets/v1/champion-sfx-audios/41.ogg",
        "title": "the Saltwater Scourge"
    },
    {
        "active": true,
        "alias": "Karma",
        "banVoPath": "/lol-game-data/assets/v1/champion-ban-vo/43.ogg",
        "baseLoadScreenPath": "/lol-game-data/assets/ASSETS/Characters/Karma/Skins/Base/KarmaLoadScreen.jpg",
        "baseSplashPath": "/lol-game-data/assets/v1/champion-splashes/43/43000.jpg",
        "botEnabled": false,
        "chooseVoPath": "/lol-game-data/assets/v1/champion-choose-vo/43.ogg",
        "disabledQueues": [],
        "freeToPlay": false,
        "id": 43,
        "name": "Karma",
        "ownership": {
            "freeToPlayReward": false,
            "owned": true,
            "rental": {
                "endDate": 0,
                "purchaseDate": 1586697004000,
                "rented": false,
                "winCountRemaining": 0
            }
        },
        "purchased": 1586697004000,
        "rankedPlayEnabled": true,
        "roles": [
            "mage",
            "support"
        ],
        "squarePortraitPath": "/lol-game-data/assets/v1/champion-icons/43.png",
        "stingerSfxPath": "/lol-game-data/assets/v1/champion-sfx-audios/43.ogg",
        "title": "the Enlightened One"
    },
    {
        "active": true,
        "alias": "Veigar",
        "banVoPath": "/lol-game-data/assets/v1/champion-ban-vo/45.ogg",
        "baseLoadScreenPath": "/lol-game-data/assets/ASSETS/Characters/Veigar/Skins/Base/VeigarLoadScreen.jpg",
        "baseSplashPath": "/lol-game-data/assets/v1/champion-splashes/45/45000.jpg",
        "botEnabled": true,
        "chooseVoPath": "/lol-game-data/assets/v1/champion-choose-vo/45.ogg",
        "disabledQueues": [],
        "freeToPlay": true,
        "id": 45,
        "name": "Veigar",
        "ownership": {
            "freeToPlayReward": false,
            "owned": false,
            "rental": {
                "endDate": 0,
                "purchaseDate": 0,
                "rented": false,
                "winCountRemaining": 0
            }
        },
        "purchased": 0,
        "rankedPlayEnabled": true,
        "roles": [
            "mage"
        ],
        "squarePortraitPath": "/lol-game-data/assets/v1/champion-icons/45.png",
        "stingerSfxPath": "/lol-game-data/assets/v1/champion-sfx-audios/45.ogg",
        "title": "the Tiny Master of Evil"
    },
    {
        "active": true,
        "alias": "Trundle",
        "banVoPath": "/lol-game-data/assets/v1/champion-ban-vo/48.ogg",
        "baseLoadScreenPath": "/lol-game-data/assets/ASSETS/Characters/Trundle/Skins/Base/TrundleLoadScreen.jpg",
        "baseSplashPath": "/lol-game-data/assets/v1/champion-splashes/48/48000.jpg",
        "botEnabled": true,
        "chooseVoPath": "/lol-game-data/assets/v1/champion-choose-vo/48.ogg",
        "disabledQueues": [],
        "freeToPlay": false,
        "id": 48,
        "name": "Trundle",
        "ownership": {
            "freeToPlayReward": false,
            "owned": true,
            "rental": {
                "endDate": 0,
                "purchaseDate": 1596385635000,
                "rented": false,
                "winCountRemaining": 0
            }
        },
        "purchased": 1596385635000,
        "rankedPlayEnabled": true,
        "roles": [
            "fighter",
            "tank"
        ],
        "squarePortraitPath": "/lol-game-data/assets/v1/champion-icons/48.png",
        "stingerSfxPath": "/lol-game-data/assets/v1/champion-sfx-audios/48.ogg",
        "title": "the Troll King"
    },
    {
        "active": true,
        "alias": "Swain",
        "banVoPath": "/lol-game-data/assets/v1/champion-ban-vo/50.ogg",
        "baseLoadScreenPath": "/lol-game-data/assets/ASSETS/Characters/Swain/Skins/Base/SwainLoadScreen.jpg",
        "baseSplashPath": "/lol-game-data/assets/v1/champion-splashes/50/50000.jpg",
        "botEnabled": false,
        "chooseVoPath": "/lol-game-data/assets/v1/champion-choose-vo/50.ogg",
        "disabledQueues": [],
        "freeToPlay": false,
        "id": 50,
        "name": "Swain",
        "ownership": {
            "freeToPlayReward": false,
            "owned": true,
            "rental": {
                "endDate": 0,
                "purchaseDate": 1583355053000,
                "rented": false,
                "winCountRemaining": 0
            }
        },
        "purchased": 1583355053000,
        "rankedPlayEnabled": true,
        "roles": [
            "mage",
            "fighter"
        ],
        "squarePortraitPath": "/lol-game-data/assets/v1/champion-icons/50.png",
        "stingerSfxPath": "/lol-game-data/assets/v1/champion-sfx-audios/50.ogg",
        "title": "the Noxian Grand General"
    },
    {
        "active": true,
        "alias": "Caitlyn",
        "banVoPath": "/lol-game-data/assets/v1/champion-ban-vo/51.ogg",
        "baseLoadScreenPath": "/lol-game-data/assets/ASSETS/Characters/Caitlyn/Skins/Base/CaitlynLoadScreen.jpg",
        "baseSplashPath": "/lol-game-data/assets/v1/champion-splashes/51/51000.jpg",
        "botEnabled": true,
        "chooseVoPath": "/lol-game-data/assets/v1/champion-choose-vo/51.ogg",
        "disabledQueues": [],
        "freeToPlay": false,
        "id": 51,
        "name": "Caitlyn",
        "ownership": {
            "freeToPlayReward": false,
            "owned": true,
            "rental": {
                "endDate": 0,
                "purchaseDate": 1595962681000,
                "rented": false,
                "winCountRemaining": 0
            }
        },
        "purchased": 1595962681000,
        "rankedPlayEnabled": true,
        "roles": [
            "marksman"
        ],
        "squarePortraitPath": "/lol-game-data/assets/v1/champion-icons/51.png",
        "stingerSfxPath": "/lol-game-data/assets/v1/champion-sfx-audios/51.ogg",
        "title": "the Sheriff of Piltover"
    },
    {
        "active": true,
        "alias": "Blitzcrank",
        "banVoPath": "/lol-game-data/assets/v1/champion-ban-vo/53.ogg",
        "baseLoadScreenPath": "/lol-game-data/assets/ASSETS/Characters/Blitzcrank/Skins/Base/BlitzcrankLoadScreen.jpg",
        "baseSplashPath": "/lol-game-data/assets/v1/champion-splashes/53/53000.jpg",
        "botEnabled": true,
        "chooseVoPath": "/lol-game-data/assets/v1/champion-choose-vo/53.ogg",
        "disabledQueues": [],
        "freeToPlay": true,
        "id": 53,
        "name": "Blitzcrank",
        "ownership": {
            "freeToPlayReward": false,
            "owned": false,
            "rental": {
                "endDate": 0,
                "purchaseDate": 0,
                "rented": false,
                "winCountRemaining": 0
            }
        },
        "purchased": 0,
        "rankedPlayEnabled": true,
        "roles": [
            "tank",
            "fighter"
        ],
        "squarePortraitPath": "/lol-game-data/assets/v1/champion-icons/53.png",
        "stingerSfxPath": "/lol-game-data/assets/v1/champion-sfx-audios/53.ogg",
        "title": "the Great Steam Golem"
    },
    {
        "active": true,
        "alias": "Katarina",
        "banVoPath": "/lol-game-data/assets/v1/champion-ban-vo/55.ogg",
        "baseLoadScreenPath": "/lol-game-data/assets/ASSETS/Characters/Katarina/Skins/Base/KatarinaLoadScreen.jpg",
        "baseSplashPath": "/lol-game-data/assets/v1/champion-splashes/55/55000.jpg",
        "botEnabled": false,
        "chooseVoPath": "/lol-game-data/assets/v1/champion-choose-vo/55.ogg",
        "disabledQueues": [],
        "freeToPlay": false,
        "id": 55,
        "name": "Katarina",
        "ownership": {
            "freeToPlayReward": false,
            "owned": true,
            "rental": {
                "endDate": 0,
                "purchaseDate": 1510957423000,
                "rented": false,
                "winCountRemaining": 0
            }
        },
        "purchased": 1510957423000,
        "rankedPlayEnabled": true,
        "roles": [
            "assassin",
            "mage"
        ],
        "squarePortraitPath": "/lol-game-data/assets/v1/champion-icons/55.png",
        "stingerSfxPath": "/lol-game-data/assets/v1/champion-sfx-audios/55.ogg",
        "title": "the Sinister Blade"
    },
    {
        "active": true,
        "alias": "JarvanIV",
        "banVoPath": "/lol-game-data/assets/v1/champion-ban-vo/59.ogg",
        "baseLoadScreenPath": "/lol-game-data/assets/ASSETS/Characters/JarvanIV/Skins/Base/JarvanIVLoadScreen.jpg",
        "baseSplashPath": "/lol-game-data/assets/v1/champion-splashes/59/59000.jpg",
        "botEnabled": false,
        "chooseVoPath": "/lol-game-data/assets/v1/champion-choose-vo/59.ogg",
        "disabledQueues": [],
        "freeToPlay": false,
        "id": 59,
        "name": "Jarvan IV",
        "ownership": {
            "freeToPlayReward": false,
            "owned": true,
            "rental": {
                "endDate": 0,
                "purchaseDate": 1519658006000,
                "rented": false,
                "winCountRemaining": 0
            }
        },
        "purchased": 1519658006000,
        "rankedPlayEnabled": true,
        "roles": [
            "tank",
            "fighter"
        ],
        "squarePortraitPath": "/lol-game-data/assets/v1/champion-icons/59.png",
        "stingerSfxPath": "/lol-game-data/assets/v1/champion-sfx-audios/59.ogg",
        "title": "the Exemplar of Demacia"
    },
    {
        "active": true,
        "alias": "Elise",
        "banVoPath": "/lol-game-data/assets/v1/champion-ban-vo/60.ogg",
        "baseLoadScreenPath": "/lol-game-data/assets/ASSETS/Characters/Elise/Skins/Base/EliseLoadScreen.jpg",
        "baseSplashPath": "/lol-game-data/assets/v1/champion-splashes/60/60000.jpg",
        "botEnabled": false,
        "chooseVoPath": "/lol-game-data/assets/v1/champion-choose-vo/60.ogg",
        "disabledQueues": [],
        "freeToPlay": false,
        "id": 60,
        "name": "Elise",
        "ownership": {
            "freeToPlayReward": false,
            "owned": true,
            "rental": {
                "endDate": 0,
                "purchaseDate": 1596385646000,
                "rented": false,
                "winCountRemaining": 0
            }
        },
        "purchased": 1596385646000,
        "rankedPlayEnabled": true,
        "roles": [
            "mage",
            "fighter"
        ],
        "squarePortraitPath": "/lol-game-data/assets/v1/champion-icons/60.png",
        "stingerSfxPath": "/lol-game-data/assets/v1/champion-sfx-audios/60.ogg",
        "title": "the Spider Queen"
    },
    {
        "active": true,
        "alias": "Orianna",
        "banVoPath": "/lol-game-data/assets/v1/champion-ban-vo/61.ogg",
        "baseLoadScreenPath": "/lol-game-data/assets/ASSETS/Characters/Orianna/Skins/Base/OriannaLoadscreen.jpg",
        "baseSplashPath": "/lol-game-data/assets/v1/champion-splashes/61/61000.jpg",
        "botEnabled": false,
        "chooseVoPath": "/lol-game-data/assets/v1/champion-choose-vo/61.ogg",
        "disabledQueues": [],
        "freeToPlay": false,
        "id": 61,
        "name": "Orianna",
        "ownership": {
            "freeToPlayReward": false,
            "owned": true,
            "rental": {
                "endDate": 0,
                "purchaseDate": 1596384714000,
                "rented": false,
                "winCountRemaining": 0
            }
        },
        "purchased": 1596384714000,
        "rankedPlayEnabled": true,
        "roles": [
            "mage",
            "support"
        ],
        "squarePortraitPath": "/lol-game-data/assets/v1/champion-icons/61.png",
        "stingerSfxPath": "/lol-game-data/assets/v1/champion-sfx-audios/61.ogg",
        "title": "the Lady of Clockwork"
    },
    {
        "active": true,
        "alias": "MonkeyKing",
        "banVoPath": "/lol-game-data/assets/v1/champion-ban-vo/62.ogg",
        "baseLoadScreenPath": "/lol-game-data/assets/ASSETS/Characters/MonkeyKing/Skins/Base/MonkeyKingLoadScreen.jpg",
        "baseSplashPath": "/lol-game-data/assets/v1/champion-splashes/62/62000.jpg",
        "botEnabled": true,
        "chooseVoPath": "/lol-game-data/assets/v1/champion-choose-vo/62.ogg",
        "disabledQueues": [],
        "freeToPlay": true,
        "id": 62,
        "name": "Wukong",
        "ownership": {
            "freeToPlayReward": false,
            "owned": false,
            "rental": {
                "endDate": 0,
                "purchaseDate": 0,
                "rented": false,
                "winCountRemaining": 0
            }
        },
        "purchased": 0,
        "rankedPlayEnabled": true,
        "roles": [
            "fighter",
            "tank"
        ],
        "squarePortraitPath": "/lol-game-data/assets/v1/champion-icons/62.png",
        "stingerSfxPath": "/lol-game-data/assets/v1/champion-sfx-audios/62.ogg",
        "title": "the Monkey King"
    },
    {
        "active": true,
        "alias": "Brand",
        "banVoPath": "/lol-game-data/assets/v1/champion-ban-vo/63.ogg",
        "baseLoadScreenPath": "/lol-game-data/assets/ASSETS/Characters/Brand/Skins/Base/BrandLoadScreen.jpg",
        "baseSplashPath": "/lol-game-data/assets/v1/champion-splashes/63/63000.jpg",
        "botEnabled": true,
        "chooseVoPath": "/lol-game-data/assets/v1/champion-choose-vo/63.ogg",
        "disabledQueues": [],
        "freeToPlay": true,
        "id": 63,
        "name": "Brand",
        "ownership": {
            "freeToPlayReward": false,
            "owned": false,
            "rental": {
                "endDate": 0,
                "purchaseDate": 0,
                "rented": false,
                "winCountRemaining": 0
            }
        },
        "purchased": 0,
        "rankedPlayEnabled": true,
        "roles": [
            "mage"
        ],
        "squarePortraitPath": "/lol-game-data/assets/v1/champion-icons/63.png",
        "stingerSfxPath": "/lol-game-data/assets/v1/champion-sfx-audios/63.ogg",
        "title": "the Burning Vengeance"
    },
    {
        "active": true,
        "alias": "LeeSin",
        "banVoPath": "/lol-game-data/assets/v1/champion-ban-vo/64.ogg",
        "baseLoadScreenPath": "/lol-game-data/assets/ASSETS/Characters/LeeSin/Skins/Base/LeeSinLoadScreen.jpg",
        "baseSplashPath": "/lol-game-data/assets/v1/champion-splashes/64/64000.jpg",
        "botEnabled": false,
        "chooseVoPath": "/lol-game-data/assets/v1/champion-choose-vo/64.ogg",
        "disabledQueues": [],
        "freeToPlay": false,
        "id": 64,
        "name": "Lee Sin",
        "ownership": {
            "freeToPlayReward": false,
            "owned": true,
            "rental": {
                "endDate": 0,
                "purchaseDate": 1513865784000,
                "rented": false,
                "winCountRemaining": 0
            }
        },
        "purchased": 1513865784000,
        "rankedPlayEnabled": true,
        "roles": [
            "fighter",
            "assassin"
        ],
        "squarePortraitPath": "/lol-game-data/assets/v1/champion-icons/64.png",
        "stingerSfxPath": "/lol-game-data/assets/v1/champion-sfx-audios/64.ogg",
        "title": "the Blind Monk"
    },
    {
        "active": true,
        "alias": "Vayne",
        "banVoPath": "/lol-game-data/assets/v1/champion-ban-vo/67.ogg",
        "baseLoadScreenPath": "/lol-game-data/assets/ASSETS/Characters/Vayne/Skins/Base/VayneLoadScreen.jpg",
        "baseSplashPath": "/lol-game-data/assets/v1/champion-splashes/67/67000.jpg",
        "botEnabled": false,
        "chooseVoPath": "/lol-game-data/assets/v1/champion-choose-vo/67.ogg",
        "disabledQueues": [],
        "freeToPlay": false,
        "id": 67,
        "name": "Vayne",
        "ownership": {
            "freeToPlayReward": false,
            "owned": true,
            "rental": {
                "endDate": 0,
                "purchaseDate": 1508783528000,
                "rented": false,
                "winCountRemaining": 0
            }
        },
        "purchased": 1508783528000,
        "rankedPlayEnabled": true,
        "roles": [
            "marksman",
            "assassin"
        ],
        "squarePortraitPath": "/lol-game-data/assets/v1/champion-icons/67.png",
        "stingerSfxPath": "/lol-game-data/assets/v1/champion-sfx-audios/67.ogg",
        "title": "the Night Hunter"
    },
    {
        "active": true,
        "alias": "Cassiopeia",
        "banVoPath": "/lol-game-data/assets/v1/champion-ban-vo/69.ogg",
        "baseLoadScreenPath": "/lol-game-data/assets/ASSETS/Characters/Cassiopeia/Skins/Base/CassiopeiaLoadScreen.jpg",
        "baseSplashPath": "/lol-game-data/assets/v1/champion-splashes/69/69000.jpg",
        "botEnabled": true,
        "chooseVoPath": "/lol-game-data/assets/v1/champion-choose-vo/69.ogg",
        "disabledQueues": [],
        "freeToPlay": false,
        "id": 69,
        "name": "Cassiopeia",
        "ownership": {
            "freeToPlayReward": false,
            "owned": true,
            "rental": {
                "endDate": 0,
                "purchaseDate": 1596384757000,
                "rented": false,
                "winCountRemaining": 0
            }
        },
        "purchased": 1596384757000,
        "rankedPlayEnabled": true,
        "roles": [
            "mage"
        ],
        "squarePortraitPath": "/lol-game-data/assets/v1/champion-icons/69.png",
        "stingerSfxPath": "/lol-game-data/assets/v1/champion-sfx-audios/69.ogg",
        "title": "the Serpent's Embrace"
    },
    {
        "active": true,
        "alias": "Heimerdinger",
        "banVoPath": "/lol-game-data/assets/v1/champion-ban-vo/74.ogg",
        "baseLoadScreenPath": "/lol-game-data/assets/ASSETS/Characters/Heimerdinger/Skins/Base/HeimerdingerLoadScreen.jpg",
        "baseSplashPath": "/lol-game-data/assets/v1/champion-splashes/74/74000.jpg",
        "botEnabled": false,
        "chooseVoPath": "/lol-game-data/assets/v1/champion-choose-vo/74.ogg",
        "disabledQueues": [],
        "freeToPlay": false,
        "id": 74,
        "name": "Heimerdinger",
        "ownership": {
            "freeToPlayReward": false,
            "owned": true,
            "rental": {
                "endDate": 0,
                "purchaseDate": 1435608114000,
                "rented": false,
                "winCountRemaining": 0
            }
        },
        "purchased": 1435608114000,
        "rankedPlayEnabled": true,
        "roles": [
            "mage",
            "support"
        ],
        "squarePortraitPath": "/lol-game-data/assets/v1/champion-icons/74.png",
        "stingerSfxPath": "/lol-game-data/assets/v1/champion-sfx-audios/74.ogg",
        "title": "the Revered Inventor"
    },
    {
        "active": true,
        "alias": "Poppy",
        "banVoPath": "/lol-game-data/assets/v1/champion-ban-vo/78.ogg",
        "baseLoadScreenPath": "/lol-game-data/assets/ASSETS/Characters/Poppy/Skins/Base/PoppyLoadScreen.jpg",
        "baseSplashPath": "/lol-game-data/assets/v1/champion-splashes/78/78000.jpg",
        "botEnabled": false,
        "chooseVoPath": "/lol-game-data/assets/v1/champion-choose-vo/78.ogg",
        "disabledQueues": [],
        "freeToPlay": false,
        "id": 78,
        "name": "Poppy",
        "ownership": {
            "freeToPlayReward": false,
            "owned": true,
            "rental": {
                "endDate": 0,
                "purchaseDate": 1433410796000,
                "rented": false,
                "winCountRemaining": 0
            }
        },
        "purchased": 1433410796000,
        "rankedPlayEnabled": true,
        "roles": [
            "tank",
            "fighter"
        ],
        "squarePortraitPath": "/lol-game-data/assets/v1/champion-icons/78.png",
        "stingerSfxPath": "/lol-game-data/assets/v1/champion-sfx-audios/78.ogg",
        "title": "Keeper of the Hammer"
    },
    {
        "active": true,
        "alias": "Gragas",
        "banVoPath": "/lol-game-data/assets/v1/champion-ban-vo/79.ogg",
        "baseLoadScreenPath": "/lol-game-data/assets/ASSETS/Characters/Gragas/Skins/Base/GragasLoadScreen.jpg",
        "baseSplashPath": "/lol-game-data/assets/v1/champion-splashes/79/79000.jpg",
        "botEnabled": false,
        "chooseVoPath": "/lol-game-data/assets/v1/champion-choose-vo/79.ogg",
        "disabledQueues": [],
        "freeToPlay": true,
        "id": 79,
        "name": "Gragas",
        "ownership": {
            "freeToPlayReward": false,
            "owned": false,
            "rental": {
                "endDate": 0,
                "purchaseDate": 0,
                "rented": false,
                "winCountRemaining": 0
            }
        },
        "purchased": 0,
        "rankedPlayEnabled": true,
        "roles": [
            "fighter",
            "mage"
        ],
        "squarePortraitPath": "/lol-game-data/assets/v1/champion-icons/79.png",
        "stingerSfxPath": "/lol-game-data/assets/v1/champion-sfx-audios/79.ogg",
        "title": "the Rabble Rouser"
    },
    {
        "active": true,
        "alias": "Pantheon",
        "banVoPath": "/lol-game-data/assets/v1/champion-ban-vo/80.ogg",
        "baseLoadScreenPath": "/lol-game-data/assets/ASSETS/Characters/Pantheon/Skins/Base/PantheonLoadscreen.jpg",
        "baseSplashPath": "/lol-game-data/assets/v1/champion-splashes/80/80000.jpg",
        "botEnabled": false,
        "chooseVoPath": "/lol-game-data/assets/v1/champion-choose-vo/80.ogg",
        "disabledQueues": [],
        "freeToPlay": false,
        "id": 80,
        "name": "Pantheon",
        "ownership": {
            "freeToPlayReward": false,
            "owned": true,
            "rental": {
                "endDate": 0,
                "purchaseDate": 1596384608000,
                "rented": false,
                "winCountRemaining": 0
            }
        },
        "purchased": 1596384608000,
        "rankedPlayEnabled": true,
        "roles": [
            "fighter",
            "assassin"
        ],
        "squarePortraitPath": "/lol-game-data/assets/v1/champion-icons/80.png",
        "stingerSfxPath": "/lol-game-data/assets/v1/champion-sfx-audios/80.ogg",
        "title": "the Unbreakable Spear"
    },
    {
        "active": true,
        "alias": "Ezreal",
        "banVoPath": "/lol-game-data/assets/v1/champion-ban-vo/81.ogg",
        "baseLoadScreenPath": "/lol-game-data/assets/ASSETS/Characters/Ezreal/Skins/Base/EzrealLoadScreen.jpg",
        "baseSplashPath": "/lol-game-data/assets/v1/champion-splashes/81/81000.jpg",
        "botEnabled": true,
        "chooseVoPath": "/lol-game-data/assets/v1/champion-choose-vo/81.ogg",
        "disabledQueues": [],
        "freeToPlay": true,
        "id": 81,
        "name": "Ezreal",
        "ownership": {
            "freeToPlayReward": false,
            "owned": true,
            "rental": {
                "endDate": 0,
                "purchaseDate": 1582933562000,
                "rented": false,
                "winCountRemaining": 0
            }
        },
        "purchased": 1582933562000,
        "rankedPlayEnabled": true,
        "roles": [
            "marksman",
            "mage"
        ],
        "squarePortraitPath": "/lol-game-data/assets/v1/champion-icons/81.png",
        "stingerSfxPath": "/lol-game-data/assets/v1/champion-sfx-audios/81.ogg",
        "title": "the Prodigal Explorer"
    },
    {
        "active": true,
        "alias": "Yorick",
        "banVoPath": "/lol-game-data/assets/v1/champion-ban-vo/83.ogg",
        "baseLoadScreenPath": "/lol-game-data/assets/ASSETS/Characters/Yorick/Skins/Base/YorickLoadScreen.jpg",
        "baseSplashPath": "/lol-game-data/assets/v1/champion-splashes/83/83000.jpg",
        "botEnabled": false,
        "chooseVoPath": "/lol-game-data/assets/v1/champion-choose-vo/83.ogg",
        "disabledQueues": [],
        "freeToPlay": true,
        "id": 83,
        "name": "Yorick",
        "ownership": {
            "freeToPlayReward": false,
            "owned": true,
            "rental": {
                "endDate": 0,
                "purchaseDate": 1498331567000,
                "rented": false,
                "winCountRemaining": 0
            }
        },
        "purchased": 1498331567000,
        "rankedPlayEnabled": true,
        "roles": [
            "fighter",
            "tank"
        ],
        "squarePortraitPath": "/lol-game-data/assets/v1/champion-icons/83.png",
        "stingerSfxPath": "/lol-game-data/assets/v1/champion-sfx-audios/83.ogg",
        "title": "Shepherd of Souls"
    },
    {
        "active": true,
        "alias": "Garen",
        "banVoPath": "/lol-game-data/assets/v1/champion-ban-vo/86.ogg",
        "baseLoadScreenPath": "/lol-game-data/assets/ASSETS/Characters/Garen/Skins/Base/GarenLoadScreen.jpg",
        "baseSplashPath": "/lol-game-data/assets/v1/champion-splashes/86/86000.jpg",
        "botEnabled": true,
        "chooseVoPath": "/lol-game-data/assets/v1/champion-choose-vo/86.ogg",
        "disabledQueues": [],
        "freeToPlay": false,
        "id": 86,
        "name": "Garen",
        "ownership": {
            "freeToPlayReward": false,
            "owned": true,
            "rental": {
                "endDate": 0,
                "purchaseDate": 1433410756000,
                "rented": false,
                "winCountRemaining": 0
            }
        },
        "purchased": 1433410756000,
        "rankedPlayEnabled": true,
        "roles": [
            "fighter",
            "tank"
        ],
        "squarePortraitPath": "/lol-game-data/assets/v1/champion-icons/86.png",
        "stingerSfxPath": "/lol-game-data/assets/v1/champion-sfx-audios/86.ogg",
        "title": "The Might of Demacia"
    },
    {
        "active": true,
        "alias": "Talon",
        "banVoPath": "/lol-game-data/assets/v1/champion-ban-vo/91.ogg",
        "baseLoadScreenPath": "/lol-game-data/assets/ASSETS/Characters/Talon/Skins/Base/TalonLoadScreen.jpg",
        "baseSplashPath": "/lol-game-data/assets/v1/champion-splashes/91/91000.jpg",
        "botEnabled": false,
        "chooseVoPath": "/lol-game-data/assets/v1/champion-choose-vo/91.ogg",
        "disabledQueues": [],
        "freeToPlay": false,
        "id": 91,
        "name": "Talon",
        "ownership": {
            "freeToPlayReward": false,
            "owned": true,
            "rental": {
                "endDate": 0,
                "purchaseDate": 1482356553000,
                "rented": false,
                "winCountRemaining": 0
            }
        },
        "purchased": 1482356553000,
        "rankedPlayEnabled": true,
        "roles": [
            "assassin"
        ],
        "squarePortraitPath": "/lol-game-data/assets/v1/champion-icons/91.png",
        "stingerSfxPath": "/lol-game-data/assets/v1/champion-sfx-audios/91.ogg",
        "title": "the Blade's Shadow"
    },
    {
        "active": true,
        "alias": "KogMaw",
        "banVoPath": "/lol-game-data/assets/v1/champion-ban-vo/96.ogg",
        "baseLoadScreenPath": "/lol-game-data/assets/ASSETS/Characters/KogMaw/Skins/Base/KogmawLoadScreen.jpg",
        "baseSplashPath": "/lol-game-data/assets/v1/champion-splashes/96/96000.jpg",
        "botEnabled": true,
        "chooseVoPath": "/lol-game-data/assets/v1/champion-choose-vo/96.ogg",
        "disabledQueues": [],
        "freeToPlay": false,
        "id": 96,
        "name": "Kog'Maw",
        "ownership": {
            "freeToPlayReward": false,
            "owned": true,
            "rental": {
                "endDate": 0,
                "purchaseDate": 1614468602000,
                "rented": false,
                "winCountRemaining": 0
            }
        },
        "purchased": 1614468602000,
        "rankedPlayEnabled": true,
        "roles": [
            "marksman",
            "mage"
        ],
        "squarePortraitPath": "/lol-game-data/assets/v1/champion-icons/96.png",
        "stingerSfxPath": "/lol-game-data/assets/v1/champion-sfx-audios/96.ogg",
        "title": "the Mouth of the Abyss"
    },
    {
        "active": true,
        "alias": "Shen",
        "banVoPath": "/lol-game-data/assets/v1/champion-ban-vo/98.ogg",
        "baseLoadScreenPath": "/lol-game-data/assets/ASSETS/Characters/Shen/Skins/Base/ShenLoadScreen.jpg",
        "baseSplashPath": "/lol-game-data/assets/v1/champion-splashes/98/98000.jpg",
        "botEnabled": true,
        "chooseVoPath": "/lol-game-data/assets/v1/champion-choose-vo/98.ogg",
        "disabledQueues": [],
        "freeToPlay": true,
        "id": 98,
        "name": "Shen",
        "ownership": {
            "freeToPlayReward": false,
            "owned": true,
            "rental": {
                "endDate": 0,
                "purchaseDate": 1614003190000,
                "rented": false,
                "winCountRemaining": 0
            }
        },
        "purchased": 1614003190000,
        "rankedPlayEnabled": true,
        "roles": [
            "tank"
        ],
        "squarePortraitPath": "/lol-game-data/assets/v1/champion-icons/98.png",
        "stingerSfxPath": "/lol-game-data/assets/v1/champion-sfx-audios/98.ogg",
        "title": "the Eye of Twilight"
    },
    {
        "active": true,
        "alias": "Graves",
        "banVoPath": "/lol-game-data/assets/v1/champion-ban-vo/104.ogg",
        "baseLoadScreenPath": "/lol-game-data/assets/ASSETS/Characters/Graves/Skins/Base/GravesLoadScreen.jpg",
        "baseSplashPath": "/lol-game-data/assets/v1/champion-splashes/104/104000.jpg",
        "botEnabled": true,
        "chooseVoPath": "/lol-game-data/assets/v1/champion-choose-vo/104.ogg",
        "disabledQueues": [],
        "freeToPlay": true,
        "id": 104,
        "name": "Graves",
        "ownership": {
            "freeToPlayReward": false,
            "owned": true,
            "rental": {
                "endDate": 0,
                "purchaseDate": 1510584829000,
                "rented": false,
                "winCountRemaining": 0
            }
        },
        "purchased": 1510584829000,
        "rankedPlayEnabled": true,
        "roles": [
            "marksman"
        ],
        "squarePortraitPath": "/lol-game-data/assets/v1/champion-icons/104.png",
        "stingerSfxPath": "/lol-game-data/assets/v1/champion-sfx-audios/104.ogg",
        "title": "the Outlaw"
    },
    {
        "active": true,
        "alias": "Volibear",
        "banVoPath": "/lol-game-data/assets/v1/champion-ban-vo/106.ogg",
        "baseLoadScreenPath": "/lol-game-data/assets/ASSETS/Characters/Volibear/Skins/Base/VolibearLoadscreen.Voli.jpg",
        "baseSplashPath": "/lol-game-data/assets/v1/champion-splashes/106/106000.jpg",
        "botEnabled": false,
        "chooseVoPath": "/lol-game-data/assets/v1/champion-choose-vo/106.ogg",
        "disabledQueues": [],
        "freeToPlay": false,
        "id": 106,
        "name": "Volibear",
        "ownership": {
            "freeToPlayReward": false,
            "owned": true,
            "rental": {
                "endDate": 0,
                "purchaseDate": 1590792455000,
                "rented": false,
                "winCountRemaining": 0
            }
        },
        "purchased": 1590792455000,
        "rankedPlayEnabled": true,
        "roles": [
            "fighter",
            "tank"
        ],
        "squarePortraitPath": "/lol-game-data/assets/v1/champion-icons/106.png",
        "stingerSfxPath": "/lol-game-data/assets/v1/champion-sfx-audios/106.ogg",
        "title": "the Relentless Storm"
    },
    {
        "active": true,
        "alias": "Fiora",
        "banVoPath": "/lol-game-data/assets/v1/champion-ban-vo/114.ogg",
        "baseLoadScreenPath": "/lol-game-data/assets/ASSETS/Characters/Fiora/Skins/Base/FioraLoadScreen.jpg",
        "baseSplashPath": "/lol-game-data/assets/v1/champion-splashes/114/114000.jpg",
        "botEnabled": false,
        "chooseVoPath": "/lol-game-data/assets/v1/champion-choose-vo/114.ogg",
        "disabledQueues": [],
        "freeToPlay": false,
        "id": 114,
        "name": "Fiora",
        "ownership": {
            "freeToPlayReward": false,
            "owned": true,
            "rental": {
                "endDate": 0,
                "purchaseDate": 1596645100000,
                "rented": false,
                "winCountRemaining": 0
            }
        },
        "purchased": 1596645100000,
        "rankedPlayEnabled": true,
        "roles": [
            "fighter",
            "assassin"
        ],
        "squarePortraitPath": "/lol-game-data/assets/v1/champion-icons/114.png",
        "stingerSfxPath": "/lol-game-data/assets/v1/champion-sfx-audios/114.ogg",
        "title": "the Grand Duelist"
    },
    {
        "active": true,
        "alias": "Ziggs",
        "banVoPath": "/lol-game-data/assets/v1/champion-ban-vo/115.ogg",
        "baseLoadScreenPath": "/lol-game-data/assets/ASSETS/Characters/Ziggs/Skins/Base/ZiggsLoadScreen.jpg",
        "baseSplashPath": "/lol-game-data/assets/v1/champion-splashes/115/115000.jpg",
        "botEnabled": true,
        "chooseVoPath": "/lol-game-data/assets/v1/champion-choose-vo/115.ogg",
        "disabledQueues": [],
        "freeToPlay": true,
        "id": 115,
        "name": "Ziggs",
        "ownership": {
            "freeToPlayReward": false,
            "owned": false,
            "rental": {
                "endDate": 0,
                "purchaseDate": 0,
                "rented": false,
                "winCountRemaining": 0
            }
        },
        "purchased": 0,
        "rankedPlayEnabled": true,
        "roles": [
            "mage"
        ],
        "squarePortraitPath": "/lol-game-data/assets/v1/champion-icons/115.png",
        "stingerSfxPath": "/lol-game-data/assets/v1/champion-sfx-audios/115.ogg",
        "title": "the Hexplosives Expert"
    },
    {
        "active": true,
        "alias": "Khazix",
        "banVoPath": "/lol-game-data/assets/v1/champion-ban-vo/121.ogg",
        "baseLoadScreenPath": "/lol-game-data/assets/ASSETS/Characters/KhaZix/Skins/Base/KhazixLoadScreen.jpg",
        "baseSplashPath": "/lol-game-data/assets/v1/champion-splashes/121/121000.jpg",
        "botEnabled": false,
        "chooseVoPath": "/lol-game-data/assets/v1/champion-choose-vo/121.ogg",
        "disabledQueues": [],
        "freeToPlay": false,
        "id": 121,
        "name": "Kha'Zix",
        "ownership": {
            "freeToPlayReward": false,
            "owned": true,
            "rental": {
                "endDate": 0,
                "purchaseDate": 1468061251000,
                "rented": false,
                "winCountRemaining": 0
            }
        },
        "purchased": 1468061251000,
        "rankedPlayEnabled": true,
        "roles": [
            "assassin"
        ],
        "squarePortraitPath": "/lol-game-data/assets/v1/champion-icons/121.png",
        "stingerSfxPath": "/lol-game-data/assets/v1/champion-sfx-audios/121.ogg",
        "title": "the Voidreaver"
    },
    {
        "active": true,
        "alias": "Darius",
        "banVoPath": "/lol-game-data/assets/v1/champion-ban-vo/122.ogg",
        "baseLoadScreenPath": "/lol-game-data/assets/ASSETS/Characters/Darius/Skins/Base/DariusLoadScreen.jpg",
        "baseSplashPath": "/lol-game-data/assets/v1/champion-splashes/122/122000.jpg",
        "botEnabled": true,
        "chooseVoPath": "/lol-game-data/assets/v1/champion-choose-vo/122.ogg",
        "disabledQueues": [],
        "freeToPlay": false,
        "id": 122,
        "name": "Darius",
        "ownership": {
            "freeToPlayReward": false,
            "owned": true,
            "rental": {
                "endDate": 0,
                "purchaseDate": 1408737245000,
                "rented": false,
                "winCountRemaining": 0
            }
        },
        "purchased": 1408737245000,
        "rankedPlayEnabled": true,
        "roles": [
            "fighter",
            "tank"
        ],
        "squarePortraitPath": "/lol-game-data/assets/v1/champion-icons/122.png",
        "stingerSfxPath": "/lol-game-data/assets/v1/champion-sfx-audios/122.ogg",
        "title": "the Hand of Noxus"
    },
    {
        "active": true,
        "alias": "Lissandra",
        "banVoPath": "/lol-game-data/assets/v1/champion-ban-vo/127.ogg",
        "baseLoadScreenPath": "/lol-game-data/assets/ASSETS/Characters/Lissandra/Skins/Base/LissandraLoadScreen.jpg",
        "baseSplashPath": "/lol-game-data/assets/v1/champion-splashes/127/127000.jpg",
        "botEnabled": false,
        "chooseVoPath": "/lol-game-data/assets/v1/champion-choose-vo/127.ogg",
        "disabledQueues": [],
        "freeToPlay": false,
        "id": 127,
        "name": "Lissandra",
        "ownership": {
            "freeToPlayReward": false,
            "owned": true,
            "rental": {
                "endDate": 0,
                "purchaseDate": 1449247478000,
                "rented": false,
                "winCountRemaining": 0
            }
        },
        "purchased": 1449247478000,
        "rankedPlayEnabled": true,
        "roles": [
            "mage"
        ],
        "squarePortraitPath": "/lol-game-data/assets/v1/champion-icons/127.png",
        "stingerSfxPath": "/lol-game-data/assets/v1/champion-sfx-audios/127.ogg",
        "title": "the Ice Witch"
    },
    {
        "active": true,
        "alias": "Quinn",
        "banVoPath": "/lol-game-data/assets/v1/champion-ban-vo/133.ogg",
        "baseLoadScreenPath": "/lol-game-data/assets/ASSETS/Characters/Quinn/Skins/Base/QuinnLoadScreen.jpg",
        "baseSplashPath": "/lol-game-data/assets/v1/champion-splashes/133/133000.jpg",
        "botEnabled": false,
        "chooseVoPath": "/lol-game-data/assets/v1/champion-choose-vo/133.ogg",
        "disabledQueues": [],
        "freeToPlay": false,
        "id": 133,
        "name": "Quinn",
        "ownership": {
            "freeToPlayReward": false,
            "owned": true,
            "rental": {
                "endDate": 0,
                "purchaseDate": 1458757483000,
                "rented": false,
                "winCountRemaining": 0
            }
        },
        "purchased": 1458757483000,
        "rankedPlayEnabled": true,
        "roles": [
            "marksman",
            "assassin"
        ],
        "squarePortraitPath": "/lol-game-data/assets/v1/champion-icons/133.png",
        "stingerSfxPath": "/lol-game-data/assets/v1/champion-sfx-audios/133.ogg",
        "title": "Demacia's Wings"
    },
    {
        "active": true,
        "alias": "AurelionSol",
        "banVoPath": "/lol-game-data/assets/v1/champion-ban-vo/136.ogg",
        "baseLoadScreenPath": "/lol-game-data/assets/ASSETS/Characters/AurelionSol/Skins/Base/AurelionSolLoadScreen.jpg",
        "baseSplashPath": "/lol-game-data/assets/v1/champion-splashes/136/136000.jpg",
        "botEnabled": false,
        "chooseVoPath": "/lol-game-data/assets/v1/champion-choose-vo/136.ogg",
        "disabledQueues": [],
        "freeToPlay": false,
        "id": 136,
        "name": "Aurelion Sol",
        "ownership": {
            "freeToPlayReward": false,
            "owned": true,
            "rental": {
                "endDate": 0,
                "purchaseDate": 1595962859000,
                "rented": false,
                "winCountRemaining": 0
            }
        },
        "purchased": 1595962859000,
        "rankedPlayEnabled": true,
        "roles": [
            "mage"
        ],
        "squarePortraitPath": "/lol-game-data/assets/v1/champion-icons/136.png",
        "stingerSfxPath": "/lol-game-data/assets/v1/champion-sfx-audios/136.ogg",
        "title": "The Star Forger"
    },
    {
        "active": true,
        "alias": "Zyra",
        "banVoPath": "/lol-game-data/assets/v1/champion-ban-vo/143.ogg",
        "baseLoadScreenPath": "/lol-game-data/assets/ASSETS/Characters/Zyra/Skins/Base/ZyraLoadScreen.jpg",
        "baseSplashPath": "/lol-game-data/assets/v1/champion-splashes/143/143000.jpg",
        "botEnabled": true,
        "chooseVoPath": "/lol-game-data/assets/v1/champion-choose-vo/143.ogg",
        "disabledQueues": [],
        "freeToPlay": false,
        "id": 143,
        "name": "Zyra",
        "ownership": {
            "freeToPlayReward": false,
            "owned": true,
            "rental": {
                "endDate": 0,
                "purchaseDate": 1482699890000,
                "rented": false,
                "winCountRemaining": 0
            }
        },
        "purchased": 1482699890000,
        "rankedPlayEnabled": true,
        "roles": [
            "mage",
            "support"
        ],
        "squarePortraitPath": "/lol-game-data/assets/v1/champion-icons/143.png",
        "stingerSfxPath": "/lol-game-data/assets/v1/champion-sfx-audios/143.ogg",
        "title": "Rise of the Thorns"
    },
    {
        "active": true,
        "alias": "Yasuo",
        "banVoPath": "/lol-game-data/assets/v1/champion-ban-vo/157.ogg",
        "baseLoadScreenPath": "/lol-game-data/assets/ASSETS/Characters/Yasuo/Skins/Base/YasuoLoadScreen.jpg",
        "baseSplashPath": "/lol-game-data/assets/v1/champion-splashes/157/157000.jpg",
        "botEnabled": false,
        "chooseVoPath": "/lol-game-data/assets/v1/champion-choose-vo/157.ogg",
        "disabledQueues": [],
        "freeToPlay": true,
        "id": 157,
        "name": "Yasuo",
        "ownership": {
            "freeToPlayReward": false,
            "owned": true,
            "rental": {
                "endDate": 0,
                "purchaseDate": 1473427545000,
                "rented": false,
                "winCountRemaining": 0
            }
        },
        "purchased": 1473427545000,
        "rankedPlayEnabled": true,
        "roles": [
            "fighter",
            "assassin"
        ],
        "squarePortraitPath": "/lol-game-data/assets/v1/champion-icons/157.png",
        "stingerSfxPath": "/lol-game-data/assets/v1/champion-sfx-audios/157.ogg",
        "title": "the Unforgiven"
    },
    {
        "active": true,
        "alias": "Velkoz",
        "banVoPath": "/lol-game-data/assets/v1/champion-ban-vo/161.ogg",
        "baseLoadScreenPath": "/lol-game-data/assets/ASSETS/Characters/Velkoz/Skins/Base/VelkozLoadScreen.jpg",
        "baseSplashPath": "/lol-game-data/assets/v1/champion-splashes/161/161000.jpg",
        "botEnabled": false,
        "chooseVoPath": "/lol-game-data/assets/v1/champion-choose-vo/161.ogg",
        "disabledQueues": [],
        "freeToPlay": false,
        "id": 161,
        "name": "Vel'Koz",
        "ownership": {
            "freeToPlayReward": false,
            "owned": true,
            "rental": {
                "endDate": 0,
                "purchaseDate": 1596384703000,
                "rented": false,
                "winCountRemaining": 0
            }
        },
        "purchased": 1596384703000,
        "rankedPlayEnabled": true,
        "roles": [
            "mage"
        ],
        "squarePortraitPath": "/lol-game-data/assets/v1/champion-icons/161.png",
        "stingerSfxPath": "/lol-game-data/assets/v1/champion-sfx-audios/161.ogg",
        "title": "the Eye of the Void"
    },
    {
        "active": true,
        "alias": "Taliyah",
        "banVoPath": "/lol-game-data/assets/v1/champion-ban-vo/163.ogg",
        "baseLoadScreenPath": "/lol-game-data/assets/ASSETS/Characters/Taliyah/Skins/Base/TaliyahLoadScreen.jpg",
        "baseSplashPath": "/lol-game-data/assets/v1/champion-splashes/163/163000.jpg",
        "botEnabled": false,
        "chooseVoPath": "/lol-game-data/assets/v1/champion-choose-vo/163.ogg",
        "disabledQueues": [],
        "freeToPlay": false,
        "id": 163,
        "name": "Taliyah",
        "ownership": {
            "freeToPlayReward": false,
            "owned": true,
            "rental": {
                "endDate": 0,
                "purchaseDate": 1590690068000,
                "rented": false,
                "winCountRemaining": 0
            }
        },
        "purchased": 1590690068000,
        "rankedPlayEnabled": true,
        "roles": [
            "mage",
            "support"
        ],
        "squarePortraitPath": "/lol-game-data/assets/v1/champion-icons/163.png",
        "stingerSfxPath": "/lol-game-data/assets/v1/champion-sfx-audios/163.ogg",
        "title": "the Stoneweaver"
    },
    {
        "active": true,
        "alias": "Camille",
        "banVoPath": "/lol-game-data/assets/v1/champion-ban-vo/164.ogg",
        "baseLoadScreenPath": "/lol-game-data/assets/ASSETS/Characters/Camille/skins/base/CamilleLoadScreen.jpg",
        "baseSplashPath": "/lol-game-data/assets/v1/champion-splashes/164/164000.jpg",
        "botEnabled": false,
        "chooseVoPath": "/lol-game-data/assets/v1/champion-choose-vo/164.ogg",
        "disabledQueues": [],
        "freeToPlay": false,
        "id": 164,
        "name": "Camille",
        "ownership": {
            "freeToPlayReward": false,
            "owned": true,
            "rental": {
                "endDate": 0,
                "purchaseDate": 1596384691000,
                "rented": false,
                "winCountRemaining": 0
            }
        },
        "purchased": 1596384691000,
        "rankedPlayEnabled": true,
        "roles": [
            "fighter",
            "tank"
        ],
        "squarePortraitPath": "/lol-game-data/assets/v1/champion-icons/164.png",
        "stingerSfxPath": "/lol-game-data/assets/v1/champion-sfx-audios/164.ogg",
        "title": "the Steel Shadow"
    },
    {
        "active": true,
        "alias": "Jhin",
        "banVoPath": "/lol-game-data/assets/v1/champion-ban-vo/202.ogg",
        "baseLoadScreenPath": "/lol-game-data/assets/ASSETS/Characters/Jhin/Skins/Base/JhinLoadScreen.jpg",
        "baseSplashPath": "/lol-game-data/assets/v1/champion-splashes/202/202000.jpg",
        "botEnabled": false,
        "chooseVoPath": "/lol-game-data/assets/v1/champion-choose-vo/202.ogg",
        "disabledQueues": [],
        "freeToPlay": false,
        "id": 202,
        "name": "Jhin",
        "ownership": {
            "freeToPlayReward": false,
            "owned": true,
            "rental": {
                "endDate": 0,
                "purchaseDate": 1581869990000,
                "rented": false,
                "winCountRemaining": 0
            }
        },
        "purchased": 1581869990000,
        "rankedPlayEnabled": true,
        "roles": [
            "marksman",
            "mage"
        ],
        "squarePortraitPath": "/lol-game-data/assets/v1/champion-icons/202.png",
        "stingerSfxPath": "/lol-game-data/assets/v1/champion-sfx-audios/202.ogg",
        "title": "the Virtuoso"
    },
    {
        "active": true,
        "alias": "Zed",
        "banVoPath": "/lol-game-data/assets/v1/champion-ban-vo/238.ogg",
        "baseLoadScreenPath": "/lol-game-data/assets/ASSETS/Characters/Zed/Skins/Base/ZedLoadScreen.jpg",
        "baseSplashPath": "/lol-game-data/assets/v1/champion-splashes/238/238000.jpg",
        "botEnabled": false,
        "chooseVoPath": "/lol-game-data/assets/v1/champion-choose-vo/238.ogg",
        "disabledQueues": [],
        "freeToPlay": false,
        "id": 238,
        "name": "Zed",
        "ownership": {
            "freeToPlayReward": false,
            "owned": true,
            "rental": {
                "endDate": 0,
                "purchaseDate": 1583354625000,
                "rented": false,
                "winCountRemaining": 0
            }
        },
        "purchased": 1583354625000,
        "rankedPlayEnabled": true,
        "roles": [
            "assassin"
        ],
        "squarePortraitPath": "/lol-game-data/assets/v1/champion-icons/238.png",
        "stingerSfxPath": "/lol-game-data/assets/v1/champion-sfx-audios/238.ogg",
        "title": "the Master of Shadows"
    },
    {
        "active": true,
        "alias": "Kled",
        "banVoPath": "/lol-game-data/assets/v1/champion-ban-vo/240.ogg",
        "baseLoadScreenPath": "/lol-game-data/assets/ASSETS/Characters/Kled/Skins/Base/KledLoadScreen.jpg",
        "baseSplashPath": "/lol-game-data/assets/v1/champion-splashes/240/240000.jpg",
        "botEnabled": false,
        "chooseVoPath": "/lol-game-data/assets/v1/champion-choose-vo/240.ogg",
        "disabledQueues": [],
        "freeToPlay": true,
        "id": 240,
        "name": "Kled",
        "ownership": {
            "freeToPlayReward": false,
            "owned": false,
            "rental": {
                "endDate": 0,
                "purchaseDate": 0,
                "rented": false,
                "winCountRemaining": 0
            }
        },
        "purchased": 0,
        "rankedPlayEnabled": true,
        "roles": [
            "fighter",
            "tank"
        ],
        "squarePortraitPath": "/lol-game-data/assets/v1/champion-icons/240.png",
        "stingerSfxPath": "/lol-game-data/assets/v1/champion-sfx-audios/240.ogg",
        "title": "the Cantankerous Cavalier"
    },
    {
        "active": true,
        "alias": "Ekko",
        "banVoPath": "/lol-game-data/assets/v1/champion-ban-vo/245.ogg",
        "baseLoadScreenPath": "/lol-game-data/assets/ASSETS/Characters/Ekko/Skins/Base/EkkoLoadScreen.jpg",
        "baseSplashPath": "/lol-game-data/assets/v1/champion-splashes/245/245000.jpg",
        "botEnabled": false,
        "chooseVoPath": "/lol-game-data/assets/v1/champion-choose-vo/245.ogg",
        "disabledQueues": [],
        "freeToPlay": false,
        "id": 245,
        "name": "Ekko",
        "ownership": {
            "freeToPlayReward": false,
            "owned": true,
            "rental": {
                "endDate": 0,
                "purchaseDate": 1491735714000,
                "rented": false,
                "winCountRemaining": 0
            }
        },
        "purchased": 1491735714000,
        "rankedPlayEnabled": true,
        "roles": [
            "assassin",
            "fighter"
        ],
        "squarePortraitPath": "/lol-game-data/assets/v1/champion-icons/245.png",
        "stingerSfxPath": "/lol-game-data/assets/v1/champion-sfx-audios/245.ogg",
        "title": "the Boy Who Shattered Time"
    },
    {
        "active": true,
        "alias": "Qiyana",
        "banVoPath": "/lol-game-data/assets/v1/champion-ban-vo/246.ogg",
        "baseLoadScreenPath": "/lol-game-data/assets/ASSETS/Characters/Qiyana/Skins/Base/QiyanaLoadScreen.jpg",
        "baseSplashPath": "/lol-game-data/assets/v1/champion-splashes/246/246000.jpg",
        "botEnabled": false,
        "chooseVoPath": "/lol-game-data/assets/v1/champion-choose-vo/246.ogg",
        "disabledQueues": [],
        "freeToPlay": false,
        "id": 246,
        "name": "Qiyana",
        "ownership": {
            "freeToPlayReward": false,
            "owned": true,
            "rental": {
                "endDate": 0,
                "purchaseDate": 1593789697000,
                "rented": false,
                "winCountRemaining": 0
            }
        },
        "purchased": 1593789697000,
        "rankedPlayEnabled": true,
        "roles": [
            "assassin",
            "fighter"
        ],
        "squarePortraitPath": "/lol-game-data/assets/v1/champion-icons/246.png",
        "stingerSfxPath": "/lol-game-data/assets/v1/champion-sfx-audios/246.ogg",
        "title": "Empress of the Elements"
    },
    {
        "active": true,
        "alias": "Vi",
        "banVoPath": "/lol-game-data/assets/v1/champion-ban-vo/254.ogg",
        "baseLoadScreenPath": "/lol-game-data/assets/ASSETS/Characters/Vi/Skins/Base/ViLoadScreen.jpg",
        "baseSplashPath": "/lol-game-data/assets/v1/champion-splashes/254/254000.jpg",
        "botEnabled": false,
        "chooseVoPath": "/lol-game-data/assets/v1/champion-choose-vo/254.ogg",
        "disabledQueues": [],
        "freeToPlay": false,
        "id": 254,
        "name": "Vi",
        "ownership": {
            "freeToPlayReward": false,
            "owned": true,
            "rental": {
                "endDate": 0,
                "purchaseDate": 1479045896000,
                "rented": false,
                "winCountRemaining": 0
            }
        },
        "purchased": 1479045896000,
        "rankedPlayEnabled": true,
        "roles": [
            "fighter",
            "assassin"
        ],
        "squarePortraitPath": "/lol-game-data/assets/v1/champion-icons/254.png",
        "stingerSfxPath": "/lol-game-data/assets/v1/champion-sfx-audios/254.ogg",
        "title": "the Piltover Enforcer"
    },
    {
        "active": true,
        "alias": "Aatrox",
        "banVoPath": "/lol-game-data/assets/v1/champion-ban-vo/266.ogg",
        "baseLoadScreenPath": "/lol-game-data/assets/ASSETS/Characters/Aatrox/Skins/Base/AatroxLoadscreen.jpg",
        "baseSplashPath": "/lol-game-data/assets/v1/champion-splashes/266/266000.jpg",
        "botEnabled": false,
        "chooseVoPath": "/lol-game-data/assets/v1/champion-choose-vo/266.ogg",
        "disabledQueues": [],
        "freeToPlay": false,
        "id": 266,
        "name": "Aatrox",
        "ownership": {
            "freeToPlayReward": false,
            "owned": true,
            "rental": {
                "endDate": 0,
                "purchaseDate": 1504884356000,
                "rented": false,
                "winCountRemaining": 0
            }
        },
        "purchased": 1504884356000,
        "rankedPlayEnabled": true,
        "roles": [
            "fighter",
            "tank"
        ],
        "squarePortraitPath": "/lol-game-data/assets/v1/champion-icons/266.png",
        "stingerSfxPath": "/lol-game-data/assets/v1/champion-sfx-audios/266.ogg",
        "title": "the Darkin Blade"
    },
    {
        "active": true,
        "alias": "Nami",
        "banVoPath": "/lol-game-data/assets/v1/champion-ban-vo/267.ogg",
        "baseLoadScreenPath": "/lol-game-data/assets/ASSETS/Characters/Nami/Skins/Base/NamiLoadScreen.jpg",
        "baseSplashPath": "/lol-game-data/assets/v1/champion-splashes/267/267000.jpg",
        "botEnabled": false,
        "chooseVoPath": "/lol-game-data/assets/v1/champion-choose-vo/267.ogg",
        "disabledQueues": [],
        "freeToPlay": false,
        "id": 267,
        "name": "Nami",
        "ownership": {
            "freeToPlayReward": false,
            "owned": true,
            "rental": {
                "endDate": 0,
                "purchaseDate": 1508585976000,
                "rented": false,
                "winCountRemaining": 0
            }
        },
        "purchased": 1508585976000,
        "rankedPlayEnabled": true,
        "roles": [
            "support",
            "mage"
        ],
        "squarePortraitPath": "/lol-game-data/assets/v1/champion-icons/267.png",
        "stingerSfxPath": "/lol-game-data/assets/v1/champion-sfx-audios/267.ogg",
        "title": "the Tidecaller"
    },
    {
        "active": true,
        "alias": "Azir",
        "banVoPath": "/lol-game-data/assets/v1/champion-ban-vo/268.ogg",
        "baseLoadScreenPath": "/lol-game-data/assets/ASSETS/Characters/Azir/Skins/Base/AzirLoadScreen.jpg",
        "baseSplashPath": "/lol-game-data/assets/v1/champion-splashes/268/268000.jpg",
        "botEnabled": false,
        "chooseVoPath": "/lol-game-data/assets/v1/champion-choose-vo/268.ogg",
        "disabledQueues": [],
        "freeToPlay": false,
        "id": 268,
        "name": "Azir",
        "ownership": {
            "freeToPlayReward": false,
            "owned": true,
            "rental": {
                "endDate": 0,
                "purchaseDate": 1506190254000,
                "rented": false,
                "winCountRemaining": 0
            }
        },
        "purchased": 1506190254000,
        "rankedPlayEnabled": true,
        "roles": [
            "mage",
            "marksman"
        ],
        "squarePortraitPath": "/lol-game-data/assets/v1/champion-icons/268.png",
        "stingerSfxPath": "/lol-game-data/assets/v1/champion-sfx-audios/268.ogg",
        "title": "the Emperor of the Sands"
    },
    {
        "active": true,
        "alias": "Thresh",
        "banVoPath": "/lol-game-data/assets/v1/champion-ban-vo/412.ogg",
        "baseLoadScreenPath": "/lol-game-data/assets/ASSETS/Characters/Thresh/Skins/Base/ThreshLoadScreen.jpg",
        "baseSplashPath": "/lol-game-data/assets/v1/champion-splashes/412/412000.jpg",
        "botEnabled": false,
        "chooseVoPath": "/lol-game-data/assets/v1/champion-choose-vo/412.ogg",
        "disabledQueues": [],
        "freeToPlay": false,
        "id": 412,
        "name": "Thresh",
        "ownership": {
            "freeToPlayReward": false,
            "owned": true,
            "rental": {
                "endDate": 0,
                "purchaseDate": 1596752736000,
                "rented": false,
                "winCountRemaining": 0
            }
        },
        "purchased": 1596752736000,
        "rankedPlayEnabled": true,
        "roles": [
            "support",
            "fighter"
        ],
        "squarePortraitPath": "/lol-game-data/assets/v1/champion-icons/412.png",
        "stingerSfxPath": "/lol-game-data/assets/v1/champion-sfx-audios/412.ogg",
        "title": "the Chain Warden"
    },
    {
        "active": true,
        "alias": "RekSai",
        "banVoPath": "/lol-game-data/assets/v1/champion-ban-vo/421.ogg",
        "baseLoadScreenPath": "/lol-game-data/assets/ASSETS/Characters/RekSai/Skins/Base/RekSaiLoadScreen.jpg",
        "baseSplashPath": "/lol-game-data/assets/v1/champion-splashes/421/421000.jpg",
        "botEnabled": false,
        "chooseVoPath": "/lol-game-data/assets/v1/champion-choose-vo/421.ogg",
        "disabledQueues": [],
        "freeToPlay": false,
        "id": 421,
        "name": "Rek'Sai",
        "ownership": {
            "freeToPlayReward": false,
            "owned": true,
            "rental": {
                "endDate": 0,
                "purchaseDate": 1593789708000,
                "rented": false,
                "winCountRemaining": 0
            }
        },
        "purchased": 1593789708000,
        "rankedPlayEnabled": true,
        "roles": [
            "fighter"
        ],
        "squarePortraitPath": "/lol-game-data/assets/v1/champion-icons/421.png",
        "stingerSfxPath": "/lol-game-data/assets/v1/champion-sfx-audios/421.ogg",
        "title": "the Void Burrower"
    },
    {
        "active": true,
        "alias": "Ivern",
        "banVoPath": "/lol-game-data/assets/v1/champion-ban-vo/427.ogg",
        "baseLoadScreenPath": "/lol-game-data/assets/ASSETS/Characters/Ivern/Skins/Base/IvernLoadScreen.jpg",
        "baseSplashPath": "/lol-game-data/assets/v1/champion-splashes/427/427000.jpg",
        "botEnabled": false,
        "chooseVoPath": "/lol-game-data/assets/v1/champion-choose-vo/427.ogg",
        "disabledQueues": [],
        "freeToPlay": true,
        "id": 427,
        "name": "Ivern",
        "ownership": {
            "freeToPlayReward": false,
            "owned": false,
            "rental": {
                "endDate": 0,
                "purchaseDate": 0,
                "rented": false,
                "winCountRemaining": 0
            }
        },
        "purchased": 0,
        "rankedPlayEnabled": true,
        "roles": [
            "support",
            "mage"
        ],
        "squarePortraitPath": "/lol-game-data/assets/v1/champion-icons/427.png",
        "stingerSfxPath": "/lol-game-data/assets/v1/champion-sfx-audios/427.ogg",
        "title": "the Green Father"
    },
    {
        "active": true,
        "alias": "Bard",
        "banVoPath": "/lol-game-data/assets/v1/champion-ban-vo/432.ogg",
        "baseLoadScreenPath": "/lol-game-data/assets/ASSETS/Characters/Bard/Skins/Base/BardLoadScreen.jpg",
        "baseSplashPath": "/lol-game-data/assets/v1/champion-splashes/432/432000.jpg",
        "botEnabled": false,
        "chooseVoPath": "/lol-game-data/assets/v1/champion-choose-vo/432.ogg",
        "disabledQueues": [],
        "freeToPlay": false,
        "id": 432,
        "name": "Bard",
        "ownership": {
            "freeToPlayReward": false,
            "owned": true,
            "rental": {
                "endDate": 0,
                "purchaseDate": 1508011422000,
                "rented": false,
                "winCountRemaining": 0
            }
        },
        "purchased": 1508011422000,
        "rankedPlayEnabled": true,
        "roles": [
            "support",
            "mage"
        ],
        "squarePortraitPath": "/lol-game-data/assets/v1/champion-icons/432.png",
        "stingerSfxPath": "/lol-game-data/assets/v1/champion-sfx-audios/432.ogg",
        "title": "the Wandering Caretaker"
    },
    {
        "active": true,
        "alias": "Sylas",
        "banVoPath": "/lol-game-data/assets/v1/champion-ban-vo/517.ogg",
        "baseLoadScreenPath": "/lol-game-data/assets/ASSETS/Characters/Sylas/Skins/Base/SylasLoadscreen.jpg",
        "baseSplashPath": "/lol-game-data/assets/v1/champion-splashes/517/517000.jpg",
        "botEnabled": false,
        "chooseVoPath": "/lol-game-data/assets/v1/champion-choose-vo/517.ogg",
        "disabledQueues": [],
        "freeToPlay": false,
        "id": 517,
        "name": "Sylas",
        "ownership": {
            "freeToPlayReward": false,
            "owned": true,
            "rental": {
                "endDate": 0,
                "purchaseDate": 1594993971000,
                "rented": false,
                "winCountRemaining": 0
            }
        },
        "purchased": 1594993971000,
        "rankedPlayEnabled": true,
        "roles": [
            "mage",
            "assassin"
        ],
        "squarePortraitPath": "/lol-game-data/assets/v1/champion-icons/517.png",
        "stingerSfxPath": "/lol-game-data/assets/v1/champion-sfx-audios/517.ogg",
        "title": "the Unshackled"
    }
]